config/__init__.py
config/config.py
config/converter.py
config/env_var_config.py
config/merger.py
stubs/__init__.py
stubs/stub.py
stubs/behaviors/__init__.py
stubs/behaviors/call_count_behavior.py
stubs/behaviors/default_behavior.py
stubs/behaviors/fake_behavior.py
stubs/behaviors/with_args_behavior.py
javascript_utils-1.0.0.dist-info/LICENSE
javascript_utils-1.0.0.dist-info/METADATA
javascript_utils-1.0.0.dist-info/WHEEL
javascript_utils-1.0.0.dist-info/top_level.txt
javascript_utils-1.0.0.dist-info/RECORD
