Metadata-Version: 2.1
Name: javascript-utils
Version: 1.0.0
Summary: Python utilities inspired by npm packages
Author-email: Robert Brieler <rob.brieler@gmail.com>
License: MIT License
Project-URL: Homepage, https://github.com/Ebojen/jsutils
Keywords: config,configuration,stubs,sinon,testing
Classifier: Programming Language :: Python :: 3
Classifier: License :: OSI Approved :: MIT License
Classifier: Operating System :: OS Independent
Requires-Python: >=3.7
License-File: LICENSE
Provides-Extra: dev
Requires-Dist: pytest ; extra == 'dev'
Requires-Dist: coverage ; extra == 'dev'
